{
  "$schema": "https://raw.githubusercontent.com/googleapis/release-please/main/schemas/config.json",
  "release-type": "simple",
  "bump-minor-pre-major": true,
  "bump-patch-for-minor-pre-major": true,
  "include-component-in-tag": true,
  "include-v-in-tag": true,
  "tag-separator": "-",
  "separate-pull-requests": false,
  "group-pull-request-title-pattern": "chore: release ${version}",
  "changelog-sections": [
    {"type": "feat", "section": "Features", "hidden": false},
    {"type": "fix", "section": "Bug Fixes", "hidden": false},
    {"type": "perf", "section": "Performance Improvements", "hidden": false},
    {"type": "revert", "section": "Reverts", "hidden": false},
    {"type": "docs", "section": "Documentation", "hidden": false},
    {"type": "style", "section": "Styles", "hidden": true},
    {"type": "chore", "section": "Miscellaneous Chores", "hidden": true},
    {"type": "refactor", "section": "Code Refactoring", "hidden": true},
    {"type": "test", "section": "Tests", "hidden": true},
    {"type": "build", "section": "Build System", "hidden": true},
    {"type": "ci", "section": "Continuous Integration", "hidden": true}
  ],
  "packages": {
    ".": {
      "release-type": "rust",
      "component": "resonance",
      "changelog-path": "CHANGELOG.md",
      "extra-files": [
        "apps/api/Cargo.toml",
        "apps/worker/Cargo.toml",
        "packages/shared-config/Cargo.toml"
      ]
    },
    "apps/web": {
      "release-type": "node",
      "component": "web",
      "changelog-path": "CHANGELOG.md"
    }
  },
  "plugins": [
    {
      "type": "cargo-workspace",
      "merge": true
    }
  ]
}
